ThingsAddDaily.py
ThingsReport.py
thingscli.py
utilities.py
thingscli-0.0.36.dist-info/LICENSE
thingscli-0.0.36.dist-info/METADATA
thingscli-0.0.36.dist-info/WHEEL
thingscli-0.0.36.dist-info/entry_points.txt
thingscli-0.0.36.dist-info/top_level.txt
thingscli-0.0.36.dist-info/RECORD
