Metadata-Version: 2.1
Name: thingscli
Version: 0.0.36
Summary: A cli tool for things3 todo app
Home-page: https://github.com/lmgibson/ThingsStats
Author: Landon Gibson
Author-email: landon.g42@gmail.com
License: UNKNOWN
Project-URL: Source, https://github.com/lmgibson/ThingsStats
Platform: UNKNOWN
Classifier: Development Status :: 3 - Alpha
Classifier: Programming Language :: Python :: 3
Classifier: License :: OSI Approved :: MIT License
Classifier: Operating System :: OS Independent
Classifier: Programming Language :: Python :: 3.6
Classifier: Programming Language :: Python :: 3.7
Classifier: Programming Language :: Python :: 3.8
Classifier: Programming Language :: Python :: 3.9
Requires-Python: >=3.6
Requires-Dist: rich
Requires-Dist: PyInquirer
Requires-Dist: click
Requires-Dist: things.py
